touchstone/__init__.py
touchstone/bindings.py
touchstone/container.py
touchstone/exceptions.py
touchstone/py.typed
touchstone/version.py
touchstone/django/__init__.py
touchstone/django/celery_task.py
touchstone/django/middleware.py
touchstone/django/properties.py
touchstone-2.0.3.dist-info/COPYING
touchstone-2.0.3.dist-info/METADATA
touchstone-2.0.3.dist-info/WHEEL
touchstone-2.0.3.dist-info/top_level.txt
touchstone-2.0.3.dist-info/zip-safe
touchstone-2.0.3.dist-info/RECORD
