Metadata-Version: 2.1
Name: touchstone
Version: 2.0.3
Summary: IoC framework driven by annotations and type hints
Home-page: https://github.com/gmaybrun/touchstone
Maintainer: gmaybrun@gmail.com
Maintainer-email: gmaybrun@gmail.com
License: UNKNOWN
Platform: UNKNOWN
Classifier: Development Status :: 5 - Production/Stable
Classifier: Intended Audience :: Developers
Classifier: Natural Language :: English
Classifier: Operating System :: OS Independent
Classifier: License :: OSI Approved :: GNU General Public License v3 (GPLv3)
Classifier: Programming Language :: Python :: 3.6
Classifier: Programming Language :: Python :: 3.7
Classifier: Programming Language :: Python :: 3.8
Classifier: Topic :: Software Development :: Libraries :: Application Frameworks
Classifier: Topic :: Software Development :: Object Brokering
Classifier: Topic :: Utilities
Classifier: Typing :: Typed
Requires-Dist: dataclasses
Provides-Extra: dist
Requires-Dist: setuptools (>=38.6.0) ; extra == 'dist'
Requires-Dist: wheel (>=0.31.0) ; extra == 'dist'
Requires-Dist: twine (>=1.11.0) ; extra == 'dist'
Provides-Extra: django
Requires-Dist: django (==2.*) ; extra == 'django'
Provides-Extra: django_celery
Requires-Dist: django (==2.*) ; extra == 'django_celery'
Requires-Dist: celery (==4.*) ; extra == 'django_celery'
Provides-Extra: djangorestframework
Requires-Dist: django (==2.*) ; extra == 'djangorestframework'
Requires-Dist: djangorestframework (==3.*) ; extra == 'djangorestframework'
Provides-Extra: tests
Requires-Dist: pytest (==5.*) ; extra == 'tests'
Requires-Dist: tox (==3.*) ; extra == 'tests'
Requires-Dist: black (==19.3b0) ; extra == 'tests'
Requires-Dist: isort (==4.*) ; extra == 'tests'
Requires-Dist: flake8 (==3.6.*) ; extra == 'tests'
Requires-Dist: flake8-tuple ; extra == 'tests'
Requires-Dist: mypy ; extra == 'tests'
Requires-Dist: docutils ; extra == 'tests'
